dbt_colibri/cli/__init__.py
dbt_colibri/cli/cli.py
dbt_colibri/lineage_extractor/__init__.py
dbt_colibri/lineage_extractor/extractor.py
dbt_colibri/lineage_extractor/lineage.py
dbt_colibri/report/__init__.py
dbt_colibri/report/generator.py
dbt_colibri/report/index.html
dbt_colibri/utils/__init__.py
dbt_colibri/utils/json_utils.py
dbt_colibri/utils/log.py
dbt_colibri/utils/parsing_utils.py
dbt_colibri-0.2.8.dist-info/licenses/LICENSE
dbt_colibri-0.2.8.dist-info/METADATA
dbt_colibri-0.2.8.dist-info/WHEEL
dbt_colibri-0.2.8.dist-info/entry_points.txt
dbt_colibri-0.2.8.dist-info/top_level.txt
dbt_colibri-0.2.8.dist-info/RECORD
