Metadata-Version: 2.4
Name: dbt-colibri
Version: 0.2.8
Summary: A column lineage parser and dashboarding tool
Author: bned
License: MIT
Classifier: Programming Language :: Python :: 3.9
Classifier: Programming Language :: Python :: 3.10
Classifier: Programming Language :: Python :: 3.11
Classifier: Programming Language :: Python :: 3.12
Classifier: Programming Language :: Python :: 3.13
Requires-Python: >=3.9
License-File: LICENSE
Requires-Dist: click>=8.1.7
Requires-Dist: sqlglot[rs]>=26.33.0
Dynamic: license-file
